[{"body_part": [{"y": 682, "x": 297, "confidence": 0.9036058783531189, "part_id": 0}, {"y": 771, "x": 288, "confidence": 0.8646247982978821, "part_id": 1}, {"y": 766, "x": 195, "confidence": 0.8640637397766113, "part_id": 2}, {"y": 934, "x": 199, "confidence": 0.928601861000061, "part_id": 3}, {"y": 1010, "x": 306, "confidence": 0.9249573945999146, "part_id": 4}, {"y": 771, "x": 368, "confidence": 0.8966452479362488, "part_id": 5}, {"y": 913, "x": 376, "confidence": 0.8973854780197144, "part_id": 6}, {"y": 1036, "x": 403, "confidence": 0.9115728139877319, "part_id": 7}, {"y": 1001, "x": 244, "confidence": 0.7901121377944946, "part_id": 8}, {"y": 1116, "x": 359, "confidence": 0.8969483971595764, "part_id": 9}, {"y": 1284, "x": 501, "confidence": 0.854196310043335, "part_id": 10}, {"y": 975, "x": 346, "confidence": 0.7159395217895508, "part_id": 11}, {"y": 1041, "x": 509, "confidence": 0.9544902443885803, "part_id": 12}, {"y": 1271, "x": 438, "confidence": 0.697181761264801, "part_id": 13}, {"y": 656, "x": 270, "confidence": 0.9244300127029419, "part_id": 14}, {"y": 656, "x": 306, "confidence": 0.8984483480453491, "part_id": 15}, {"y": 673, "x": 252, "confidence": 0.8700137138366699, "part_id": 16}, {"y": 669, "x": 337, "confidence": 0.9156365394592285, "part_id": 17}], "image_size": {"width": 1600, "height": 1200}, "face_landmark": []}, {"body_part": [{"y": 660, "x": 864, "confidence": 0.9339349865913391, "part_id": 0}, {"y": 757, "x": 890, "confidence": 0.8544374704360962, "part_id": 1}, {"y": 758, "x": 802, "confidence": 0.8698273301124573, "part_id": 2}, {"y": 863, "x": 731, "confidence": 0.9206143617630005, "part_id": 3}, {"y": 926, "x": 753, "confidence": 0.6757774949073792, "part_id": 4}, {"y": 757, "x": 970, "confidence": 0.8914427757263184, "part_id": 5}, {"y": 877, "x": 970, "confidence": 0.7775519490242004, "part_id": 6}, {"y": 957, "x": 824, "confidence": 0.898989200592041, "part_id": 7}, {"y": 970, "x": 859, "confidence": 0.7200160622596741, "part_id": 8}, {"y": 939, "x": 696, "confidence": 0.8541562557220459, "part_id": 9}, {"y": 1165, "x": 722, "confidence": 0.8459655046463013, "part_id": 10}, {"y": 966, "x": 952, "confidence": 0.648094892501831, "part_id": 11}, {"y": 935, "x": 970, "confidence": 0.8715474605560303, "part_id": 12}, {"y": 1209, "x": 979, "confidence": 0.8046802282333374, "part_id": 13}, {"y": 651, "x": 842, "confidence": 0.9181400537490845, "part_id": 14}, {"y": 647, "x": 881, "confidence": 0.8886445164680481, "part_id": 15}, {"y": 664, "x": 828, "confidence": 0.8157086372375488, "part_id": 16}, {"y": 656, "x": 912, "confidence": 0.9447550773620605, "part_id": 17}], "image_size": {"width": 1600, "height": 1200}, "face_landmark": []}]