[{"body_part": [{"y": 1489, "x": 851, "confidence": 1.060455560684204, "part_id": 0}, {"y": 1724, "x": 594, "confidence": 0.9048720002174377, "part_id": 1}, {"y": 1735, "x": 481, "confidence": 0.8441067337989807, "part_id": 2}, {"y": 2206, "x": 437, "confidence": 0.9062803387641907, "part_id": 3}, {"y": 2161, "x": 839, "confidence": 0.8799312710762024, "part_id": 4}, {"y": 1735, "x": 750, "confidence": 0.9596570730209351, "part_id": 5}, {"y": 2026, "x": 761, "confidence": 0.728329598903656, "part_id": 6}, {"y": 2138, "x": 873, "confidence": 0.5912202596664429, "part_id": 7}, {"y": 2374, "x": 325, "confidence": 0.7166559100151062, "part_id": 8}, {"y": 2340, "x": 694, "confidence": 0.8506183624267578, "part_id": 9}, {"y": 2967, "x": 784, "confidence": 0.771507978439331, "part_id": 10}, {"y": 2239, "x": 627, "confidence": 0.5552718639373779, "part_id": 11}, {"y": 0, "x": 0, "confidence": 0.0, "part_id": 12}, {"y": 0, "x": 0, "confidence": 0.0, "part_id": 13}, {"y": 0, "x": 0, "confidence": 0.0, "part_id": 14}, {"y": 0, "x": 0, "confidence": 0.0, "part_id": 15}, {"y": 1467, "x": 672, "confidence": 0.983805775642395, "part_id": 16}, {"y": 0, "x": 0, "confidence": 0.0, "part_id": 17}], "imageSize": {"width": 4032, "height": 3024}, "face_landmark": []}, {"body_part": [{"y": 0, "x": 0, "confidence": 0.0, "part_id": 0}, {"y": 1803, "x": 1411, "confidence": 0.7553402185440063, "part_id": 1}, {"y": 1780, "x": 1344, "confidence": 0.8901077508926392, "part_id": 2}, {"y": 2071, "x": 1388, "confidence": 1.0678114891052246, "part_id": 3}, {"y": 2038, "x": 1568, "confidence": 1.0331521034240723, "part_id": 4}, {"y": 1825, "x": 1512, "confidence": 0.7112632989883423, "part_id": 5}, {"y": 2004, "x": 1623, "confidence": 0.5772891044616699, "part_id": 6}, {"y": 2060, "x": 1634, "confidence": 0.5464188456535339, "part_id": 7}, {"y": 2105, "x": 1198, "confidence": 0.5956363677978516, "part_id": 8}, {"y": 2127, "x": 1556, "confidence": 0.9294208884239197, "part_id": 9}, {"y": 2519, "x": 1534, "confidence": 0.8060816526412964, "part_id": 10}, {"y": 2105, "x": 1344, "confidence": 0.5288659334182739, "part_id": 11}, {"y": 2105, "x": 1645, "confidence": 0.8668088912963867, "part_id": 12}, {"y": 2474, "x": 1567, "confidence": 0.7898743748664856, "part_id": 13}, {"y": 0, "x": 0, "confidence": 0.0, "part_id": 14}, {"y": 0, "x": 0, "confidence": 0.0, "part_id": 15}, {"y": 0, "x": 0, "confidence": 0.0, "part_id": 16}, {"y": 0, "x": 0, "confidence": 0.0, "part_id": 17}], "imageSize": {"width": 4032, "height": 3024}, "face_landmark": []}, {"body_part": [{"y": 1433, "x": 2004, "confidence": 0.457373708486557, "part_id": 0}, {"y": 1635, "x": 2262, "confidence": 0.7870962023735046, "part_id": 1}, {"y": 1568, "x": 2362, "confidence": 0.6774865984916687, "part_id": 2}, {"y": 1937, "x": 2363, "confidence": 0.06920219212770462, "part_id": 3}, {"y": 0, "x": 0, "confidence": 0.0, "part_id": 4}, {"y": 1657, "x": 2150, "confidence": 0.8790985941886902, "part_id": 5}, {"y": 1926, "x": 2082, "confidence": 0.6582250595092773, "part_id": 6}, {"y": 1926, "x": 1926, "confidence": 0.6961341500282288, "part_id": 7}, {"y": 2228, "x": 2351, "confidence": 0.6666500568389893, "part_id": 8}, {"y": 2911, "x": 2295, "confidence": 0.7566527724266052, "part_id": 9}, {"y": 3359, "x": 2295, "confidence": 0.869038999080658, "part_id": 10}, {"y": 2306, "x": 2184, "confidence": 0.7067199945449829, "part_id": 11}, {"y": 2978, "x": 2183, "confidence": 0.881727397441864, "part_id": 12}, {"y": 3527, "x": 2183, "confidence": 0.863170862197876, "part_id": 13}, {"y": 0, "x": 0, "confidence": 0.0, "part_id": 14}, {"y": 1400, "x": 2016, "confidence": 0.5401585698127747, "part_id": 15}, {"y": 0, "x": 0, "confidence": 0.0, "part_id": 16}, {"y": 1456, "x": 2116, "confidence": 0.7946155667304993, "part_id": 17}], "imageSize": {"width": 4032, "height": 3024}, "face_landmark": []}, {"body_part": [{"y": 1646, "x": 1030, "confidence": 0.8958107233047485, "part_id": 0}, {"y": 1813, "x": 885, "confidence": 0.7981324791908264, "part_id": 1}, {"y": 1780, "x": 784, "confidence": 0.7445240616798401, "part_id": 2}, {"y": 2038, "x": 1019, "confidence": 0.5421472787857056, "part_id": 3}, {"y": 1769, "x": 996, "confidence": 0.25033390522003174, "part_id": 4}, {"y": 1802, "x": 1007, "confidence": 0.6793935894966125, "part_id": 5}, {"y": 2026, "x": 1041, "confidence": 0.7477350831031799, "part_id": 6}, {"y": 1803, "x": 1019, "confidence": 0.8365430235862732, "part_id": 7}, {"y": 2183, "x": 862, "confidence": 0.3308888077735901, "part_id": 8}, {"y": 2172, "x": 1164, "confidence": 0.5041085481643677, "part_id": 9}, {"y": 0, "x": 0, "confidence": 0.0, "part_id": 10}, {"y": 2172, "x": 1008, "confidence": 0.35994571447372437, "part_id": 11}, {"y": 2195, "x": 1120, "confidence": 1.0717495679855347, "part_id": 12}, {"y": 2788, "x": 1075, "confidence": 0.7655771374702454, "part_id": 13}, {"y": 1466, "x": 840, "confidence": 0.996457576751709, "part_id": 14}, {"y": 1635, "x": 1041, "confidence": 0.23507004976272583, "part_id": 15}, {"y": 1467, "x": 672, "confidence": 0.983805775642395, "part_id": 16}, {"y": 0, "x": 0, "confidence": 0.0, "part_id": 17}], "imageSize": {"width": 4032, "height": 3024}, "face_landmark": []}, {"body_part": [{"y": 1713, "x": 1668, "confidence": 0.9437736868858337, "part_id": 0}, {"y": 1803, "x": 1511, "confidence": 0.7267103791236877, "part_id": 1}, {"y": 1791, "x": 1534, "confidence": 0.6974306106567383, "part_id": 2}, {"y": 0, "x": 0, "confidence": 0.0, "part_id": 3}, {"y": 0, "x": 0, "confidence": 0.0, "part_id": 4}, {"y": 1814, "x": 1612, "confidence": 0.7145622968673706, "part_id": 5}, {"y": 0, "x": 0, "confidence": 0.0, "part_id": 6}, {"y": 0, "x": 0, "confidence": 0.0, "part_id": 7}, {"y": 2015, "x": 1557, "confidence": 0.09362294524908066, "part_id": 8}, {"y": 0, "x": 0, "confidence": 0.0, "part_id": 9}, {"y": 0, "x": 0, "confidence": 0.0, "part_id": 10}, {"y": 0, "x": 0, "confidence": 0.0, "part_id": 11}, {"y": 0, "x": 0, "confidence": 0.0, "part_id": 12}, {"y": 0, "x": 0, "confidence": 0.0, "part_id": 13}, {"y": 1668, "x": 1646, "confidence": 1.0207206010818481, "part_id": 14}, {"y": 1668, "x": 1713, "confidence": 0.5572779178619385, "part_id": 15}, {"y": 1668, "x": 1556, "confidence": 1.032804012298584, "part_id": 16}, {"y": 0, "x": 0, "confidence": 0.0, "part_id": 17}], "imageSize": {"width": 4032, "height": 3024}, "face_landmark": []}, {"body_part": [{"y": 0, "x": 0, "confidence": 0.0, "part_id": 0}, {"y": 0, "x": 0, "confidence": 0.0, "part_id": 1}, {"y": 0, "x": 0, "confidence": 0.0, "part_id": 2}, {"y": 0, "x": 0, "confidence": 0.0, "part_id": 3}, {"y": 0, "x": 0, "confidence": 0.0, "part_id": 4}, {"y": 0, "x": 0, "confidence": 0.0, "part_id": 5}, {"y": 0, "x": 0, "confidence": 0.0, "part_id": 6}, {"y": 0, "x": 0, "confidence": 0.0, "part_id": 7}, {"y": 0, "x": 0, "confidence": 0.0, "part_id": 8}, {"y": 0, "x": 0, "confidence": 0.0, "part_id": 9}, {"y": 0, "x": 0, "confidence": 0.0, "part_id": 10}, {"y": 2094, "x": 2475, "confidence": 0.32061007618904114, "part_id": 11}, {"y": 2418, "x": 2463, "confidence": 0.7040171027183533, "part_id": 12}, {"y": 2732, "x": 2474, "confidence": 0.7809134125709534, "part_id": 13}, {"y": 0, "x": 0, "confidence": 0.0, "part_id": 14}, {"y": 0, "x": 0, "confidence": 0.0, "part_id": 15}, {"y": 0, "x": 0, "confidence": 0.0, "part_id": 16}, {"y": 0, "x": 0, "confidence": 0.0, "part_id": 17}], "imageSize": {"width": 4032, "height": 3024}, "face_landmark": []}]