[{"body_part": [{"y": 1288, "x": 1624, "confidence": 0.8631369471549988, "part_id": 0}, {"y": 1299, "x": 1310, "confidence": 0.8325914740562439, "part_id": 1}, {"y": 1355, "x": 1377, "confidence": 0.7712251543998718, "part_id": 2}, {"y": 1657, "x": 1735, "confidence": 0.9143885374069214, "part_id": 3}, {"y": 1377, "x": 1735, "confidence": 0.5405592322349548, "part_id": 4}, {"y": 1254, "x": 1265, "confidence": 0.664350152015686, "part_id": 5}, {"y": 1467, "x": 1478, "confidence": 0.16831305623054504, "part_id": 6}, {"y": 0, "x": 0, "confidence": 0.0, "part_id": 7}, {"y": 1971, "x": 1164, "confidence": 0.7094393968582153, "part_id": 8}, {"y": 2082, "x": 1747, "confidence": 0.8754736185073853, "part_id": 9}, {"y": 2508, "x": 1366, "confidence": 0.8133992552757263, "part_id": 10}, {"y": 1926, "x": 1120, "confidence": 0.45314937829971313, "part_id": 11}, {"y": 1982, "x": 1645, "confidence": 0.46134471893310547, "part_id": 12}, {"y": 2463, "x": 1209, "confidence": 0.8201024532318115, "part_id": 13}, {"y": 1209, "x": 1635, "confidence": 0.9152296185493469, "part_id": 14}, {"y": 0, "x": 0, "confidence": 0.0, "part_id": 15}, {"y": 1142, "x": 1534, "confidence": 0.8601155281066895, "part_id": 16}, {"y": 0, "x": 0, "confidence": 0.0, "part_id": 17}], "image_size": {"width": 4032, "height": 3024}, "face_landmark": []}]