[{"body_part": [{"y": 15, "x": 33, "confidence": 0.8223495483398438, "part_id": 0}, {"y": 31, "x": 29, "confidence": 0.7939369678497314, "part_id": 1}, {"y": 30, "x": 15, "confidence": 0.7187676429748535, "part_id": 2}, {"y": 53, "x": 5, "confidence": 0.7662162184715271, "part_id": 3}, {"y": 41, "x": 18, "confidence": 0.7402206659317017, "part_id": 4}, {"y": 34, "x": 43, "confidence": 0.7415848970413208, "part_id": 5}, {"y": 54, "x": 45, "confidence": 0.3101786673069, "part_id": 6}, {"y": 59, "x": 45, "confidence": 0.1618148386478424, "part_id": 7}, {"y": 77, "x": 16, "confidence": 0.5756841897964478, "part_id": 8}, {"y": 110, "x": 14, "confidence": 0.6482778787612915, "part_id": 9}, {"y": 143, "x": 16, "confidence": 0.6802279353141785, "part_id": 10}, {"y": 78, "x": 35, "confidence": 0.555605411529541, "part_id": 11}, {"y": 112, "x": 34, "confidence": 0.6200172305107117, "part_id": 12}, {"y": 142, "x": 30, "confidence": 0.7053815722465515, "part_id": 13}, {"y": 12, "x": 30, "confidence": 0.8370703458786011, "part_id": 14}, {"y": 12, "x": 37, "confidence": 0.847830057144165, "part_id": 15}, {"y": 12, "x": 23, "confidence": 0.6070111989974976, "part_id": 16}, {"y": 15, "x": 41, "confidence": 0.48929548263549805, "part_id": 17}], "image_size": {"width": 168, "height": 84}, "face_landmark": []}, {"body_part": [{"y": 27, "x": 61, "confidence": 0.8499619364738464, "part_id": 0}, {"y": 41, "x": 63, "confidence": 0.8452154397964478, "part_id": 1}, {"y": 39, "x": 50, "confidence": 0.6669616103172302, "part_id": 2}, {"y": 58, "x": 43, "confidence": 0.466389536857605, "part_id": 3}, {"y": 62, "x": 51, "confidence": 0.5015538930892944, "part_id": 4}, {"y": 41, "x": 77, "confidence": 0.802815318107605, "part_id": 5}, {"y": 60, "x": 81, "confidence": 0.7199732065200806, "part_id": 6}, {"y": 75, "x": 80, "confidence": 0.6651860475540161, "part_id": 7}, {"y": 82, "x": 53, "confidence": 0.5062912702560425, "part_id": 8}, {"y": 114, "x": 56, "confidence": 0.5956480503082275, "part_id": 9}, {"y": 144, "x": 60, "confidence": 0.5713005661964417, "part_id": 10}, {"y": 83, "x": 70, "confidence": 0.5390357971191406, "part_id": 11}, {"y": 115, "x": 69, "confidence": 0.5644054412841797, "part_id": 12}, {"y": 141, "x": 63, "confidence": 0.5276670455932617, "part_id": 13}, {"y": 24, "x": 59, "confidence": 0.8495663404464722, "part_id": 14}, {"y": 24, "x": 64, "confidence": 0.859969437122345, "part_id": 15}, {"y": 26, "x": 55, "confidence": 0.3573645353317261, "part_id": 16}, {"y": 26, "x": 70, "confidence": 0.8648446202278137, "part_id": 17}], "image_size": {"width": 168, "height": 84}, "face_landmark": []}]