[{"body_part": [{"y": 205, "x": 380, "confidence": 0.9023903608322144, "part_id": 0}, {"y": 242, "x": 403, "confidence": 0.8799729943275452, "part_id": 1}, {"y": 240, "x": 374, "confidence": 0.8583962917327881, "part_id": 2}, {"y": 290, "x": 357, "confidence": 0.8918039202690125, "part_id": 3}, {"y": 255, "x": 363, "confidence": 0.6074482798576355, "part_id": 4}, {"y": 242, "x": 430, "confidence": 0.848971426486969, "part_id": 5}, {"y": 307, "x": 438, "confidence": 0.8827589154243469, "part_id": 6}, {"y": 353, "x": 426, "confidence": 0.9589856863021851, "part_id": 7}, {"y": 338, "x": 374, "confidence": 0.8139238357543945, "part_id": 8}, {"y": 428, "x": 382, "confidence": 0.8186439871788025, "part_id": 9}, {"y": 512, "x": 395, "confidence": 0.8864067196846008, "part_id": 10}, {"y": 340, "x": 409, "confidence": 0.8340363502502441, "part_id": 11}, {"y": 432, "x": 405, "confidence": 0.9014266729354858, "part_id": 12}, {"y": 522, "x": 424, "confidence": 0.9025392532348633, "part_id": 13}, {"y": 198, "x": 376, "confidence": 0.7556647658348083, "part_id": 14}, {"y": 194, "x": 390, "confidence": 0.9177671074867249, "part_id": 15}, {"y": 0, "x": 0, "confidence": 0.0, "part_id": 16}, {"y": 202, "x": 409, "confidence": 0.8696581721305847, "part_id": 17}], "image_size": {"width": 767, "height": 1024}, "face_landmark": []}, {"body_part": [{"y": 223, "x": 750, "confidence": 0.8842257857322693, "part_id": 0}, {"y": 259, "x": 791, "confidence": 0.9482660889625549, "part_id": 1}, {"y": 259, "x": 760, "confidence": 0.9038622379302979, "part_id": 2}, {"y": 0, "x": 0, "confidence": 0.0, "part_id": 3}, {"y": 0, "x": 0, "confidence": 0.0, "part_id": 4}, {"y": 257, "x": 823, "confidence": 0.8969959020614624, "part_id": 5}, {"y": 324, "x": 844, "confidence": 0.8809090852737427, "part_id": 6}, {"y": 378, "x": 860, "confidence": 0.7947342395782471, "part_id": 7}, {"y": 393, "x": 775, "confidence": 0.6952104568481445, "part_id": 8}, {"y": 480, "x": 806, "confidence": 0.7687929272651672, "part_id": 9}, {"y": 566, "x": 858, "confidence": 0.8227571249008179, "part_id": 10}, {"y": 393, "x": 795, "confidence": 0.7459508776664734, "part_id": 11}, {"y": 491, "x": 758, "confidence": 0.8291873931884766, "part_id": 12}, {"y": 589, "x": 735, "confidence": 0.7333453297615051, "part_id": 13}, {"y": 211, "x": 745, "confidence": 0.8062785863876343, "part_id": 14}, {"y": 209, "x": 760, "confidence": 0.9681794047355652, "part_id": 15}, {"y": 0, "x": 0, "confidence": 0.0, "part_id": 16}, {"y": 211, "x": 789, "confidence": 0.9162169694900513, "part_id": 17}], "image_size": {"width": 767, "height": 1024}, "face_landmark": []}, {"body_part": [{"y": 225, "x": 608, "confidence": 0.848669707775116, "part_id": 0}, {"y": 274, "x": 651, "confidence": 0.7890785932540894, "part_id": 1}, {"y": 271, "x": 639, "confidence": 0.7080249786376953, "part_id": 2}, {"y": 336, "x": 622, "confidence": 0.258946031332016, "part_id": 3}, {"y": 317, "x": 587, "confidence": 0.4769119620323181, "part_id": 4}, {"y": 278, "x": 662, "confidence": 0.7643759250640869, "part_id": 5}, {"y": 355, "x": 628, "confidence": 0.5886362791061401, "part_id": 6}, {"y": 323, "x": 585, "confidence": 0.6955524682998657, "part_id": 7}, {"y": 426, "x": 641, "confidence": 0.4720498025417328, "part_id": 8}, {"y": 562, "x": 670, "confidence": 0.703140377998352, "part_id": 9}, {"y": 645, "x": 764, "confidence": 0.6724362969398499, "part_id": 10}, {"y": 432, "x": 645, "confidence": 0.6375173330307007, "part_id": 11}, {"y": 566, "x": 605, "confidence": 0.7172712683677673, "part_id": 12}, {"y": 697, "x": 593, "confidence": 0.8360313177108765, "part_id": 13}, {"y": 211, "x": 608, "confidence": 0.10059280693531036, "part_id": 14}, {"y": 217, "x": 614, "confidence": 0.7432820796966553, "part_id": 15}, {"y": 0, "x": 0, "confidence": 0.0, "part_id": 16}, {"y": 219, "x": 643, "confidence": 0.7093873620033264, "part_id": 17}], "image_size": {"width": 767, "height": 1024}, "face_landmark": []}, {"body_part": [{"y": 221, "x": 35, "confidence": 0.8124318718910217, "part_id": 0}, {"y": 236, "x": 94, "confidence": 0.7300816178321838, "part_id": 1}, {"y": 226, "x": 108, "confidence": 0.6856628060340881, "part_id": 2}, {"y": 292, "x": 132, "confidence": 0.07384655624628067, "part_id": 3}, {"y": 0, "x": 0, "confidence": 0.0, "part_id": 4}, {"y": 242, "x": 86, "confidence": 0.7905830144882202, "part_id": 5}, {"y": 328, "x": 86, "confidence": 0.7038021087646484, "part_id": 6}, {"y": 388, "x": 52, "confidence": 0.642266035079956, "part_id": 7}, {"y": 374, "x": 109, "confidence": 0.5860992670059204, "part_id": 8}, {"y": 484, "x": 81, "confidence": 0.7175708413124084, "part_id": 9}, {"y": 605, "x": 84, "confidence": 0.754666268825531, "part_id": 10}, {"y": 376, "x": 88, "confidence": 0.6270059943199158, "part_id": 11}, {"y": 488, "x": 46, "confidence": 0.8749701976776123, "part_id": 12}, {"y": 566, "x": 142, "confidence": 0.7569988965988159, "part_id": 13}, {"y": 0, "x": 0, "confidence": 0.0, "part_id": 14}, {"y": 209, "x": 31, "confidence": 0.8113874793052673, "part_id": 15}, {"y": 0, "x": 0, "confidence": 0.0, "part_id": 16}, {"y": 194, "x": 48, "confidence": 0.8762620687484741, "part_id": 17}], "image_size": {"width": 767, "height": 1024}, "face_landmark": []}, {"body_part": [{"y": 209, "x": 864, "confidence": 0.3987707793712616, "part_id": 0}, {"y": 232, "x": 848, "confidence": 0.699122965335846, "part_id": 1}, {"y": 236, "x": 850, "confidence": 0.7085789442062378, "part_id": 2}, {"y": 261, "x": 873, "confidence": 0.8922260403633118, "part_id": 3}, {"y": 228, "x": 875, "confidence": 0.5838376879692078, "part_id": 4}, {"y": 0, "x": 0, "confidence": 0.0, "part_id": 5}, {"y": 0, "x": 0, "confidence": 0.0, "part_id": 6}, {"y": 0, "x": 0, "confidence": 0.0, "part_id": 7}, {"y": 303, "x": 860, "confidence": 0.6990039944648743, "part_id": 8}, {"y": 357, "x": 864, "confidence": 0.5786546468734741, "part_id": 9}, {"y": 418, "x": 856, "confidence": 0.33854207396507263, "part_id": 10}, {"y": 297, "x": 860, "confidence": 0.479414701461792, "part_id": 11}, {"y": 353, "x": 873, "confidence": 0.3144010305404663, "part_id": 12}, {"y": 409, "x": 858, "confidence": 0.4126114845275879, "part_id": 13}, {"y": 207, "x": 860, "confidence": 0.41778552532196045, "part_id": 14}, {"y": 0, "x": 0, "confidence": 0.0, "part_id": 15}, {"y": 207, "x": 856, "confidence": 0.5804250240325928, "part_id": 16}, {"y": 0, "x": 0, "confidence": 0.0, "part_id": 17}], "image_size": {"width": 767, "height": 1024}, "face_landmark": []}]