[{"body_part": [{"y": 33, "x": 289, "confidence": 0.7467774152755737, "part_id": 0}, {"y": 57, "x": 320, "confidence": 0.5989170074462891, "part_id": 1}, {"y": 57, "x": 314, "confidence": 0.3671643137931824, "part_id": 2}, {"y": 90, "x": 294, "confidence": 0.05634116381406784, "part_id": 3}, {"y": 0, "x": 0, "confidence": 0.0, "part_id": 4}, {"y": 57, "x": 328, "confidence": 0.7861199975013733, "part_id": 5}, {"y": 84, "x": 290, "confidence": 0.841245710849762, "part_id": 6}, {"y": 51, "x": 288, "confidence": 0.678253710269928, "part_id": 7}, {"y": 159, "x": 310, "confidence": 0.5165167450904846, "part_id": 8}, {"y": 239, "x": 294, "confidence": 0.6684917211532593, "part_id": 9}, {"y": 294, "x": 264, "confidence": 0.6119675636291504, "part_id": 10}, {"y": 159, "x": 331, "confidence": 0.5482202172279358, "part_id": 11}, {"y": 228, "x": 352, "confidence": 0.6890869140625, "part_id": 12}, {"y": 285, "x": 377, "confidence": 0.4183982014656067, "part_id": 13}, {"y": 30, "x": 288, "confidence": 0.06194527447223663, "part_id": 14}, {"y": 28, "x": 291, "confidence": 0.826359748840332, "part_id": 15}, {"y": 0, "x": 0, "confidence": 0.0, "part_id": 16}, {"y": 26, "x": 310, "confidence": 0.7299867868423462, "part_id": 17}], "image_size": {"width": 314, "height": 628}, "face_landmark": []}, {"body_part": [{"y": 159, "x": 485, "confidence": 0.20914357900619507, "part_id": 0}, {"y": 161, "x": 484, "confidence": 0.535152792930603, "part_id": 1}, {"y": 161, "x": 481, "confidence": 0.5191554427146912, "part_id": 2}, {"y": 167, "x": 481, "confidence": 0.48065146803855896, "part_id": 3}, {"y": 173, "x": 482, "confidence": 0.4041513204574585, "part_id": 4}, {"y": 161, "x": 487, "confidence": 0.5168312788009644, "part_id": 5}, {"y": 167, "x": 488, "confidence": 0.39481163024902344, "part_id": 6}, {"y": 173, "x": 488, "confidence": 0.29107189178466797, "part_id": 7}, {"y": 173, "x": 483, "confidence": 0.49549996852874756, "part_id": 8}, {"y": 182, "x": 484, "confidence": 0.32843661308288574, "part_id": 9}, {"y": 193, "x": 485, "confidence": 0.12961769104003906, "part_id": 10}, {"y": 173, "x": 487, "confidence": 0.5185495615005493, "part_id": 11}, {"y": 182, "x": 487, "confidence": 0.3676625192165375, "part_id": 12}, {"y": 192, "x": 488, "confidence": 0.23599986732006073, "part_id": 13}, {"y": 158, "x": 484, "confidence": 0.20300281047821045, "part_id": 14}, {"y": 159, "x": 486, "confidence": 0.15153959393501282, "part_id": 15}, {"y": 157, "x": 483, "confidence": 0.1600596308708191, "part_id": 16}, {"y": 159, "x": 487, "confidence": 0.061878502368927, "part_id": 17}], "image_size": {"width": 314, "height": 628}, "face_landmark": []}, {"body_part": [{"y": 0, "x": 0, "confidence": 0.0, "part_id": 0}, {"y": 172, "x": 38, "confidence": 0.4788587689399719, "part_id": 1}, {"y": 172, "x": 43, "confidence": 0.4464699625968933, "part_id": 2}, {"y": 176, "x": 43, "confidence": 0.2944648563861847, "part_id": 3}, {"y": 0, "x": 0, "confidence": 0.0, "part_id": 4}, {"y": 172, "x": 38, "confidence": 0.4356916546821594, "part_id": 5}, {"y": 177, "x": 38, "confidence": 0.12530776858329773, "part_id": 6}, {"y": 180, "x": 38, "confidence": 0.059770725667476654, "part_id": 7}, {"y": 182, "x": 43, "confidence": 0.529381513595581, "part_id": 8}, {"y": 194, "x": 43, "confidence": 0.5275745391845703, "part_id": 9}, {"y": 205, "x": 41, "confidence": 0.31616660952568054, "part_id": 10}, {"y": 182, "x": 38, "confidence": 0.5153325796127319, "part_id": 11}, {"y": 194, "x": 38, "confidence": 0.4644966423511505, "part_id": 12}, {"y": 202, "x": 38, "confidence": 0.25785714387893677, "part_id": 13}, {"y": 0, "x": 0, "confidence": 0.0, "part_id": 14}, {"y": 0, "x": 0, "confidence": 0.0, "part_id": 15}, {"y": 166, "x": 44, "confidence": 0.13073445856571198, "part_id": 16}, {"y": 167, "x": 40, "confidence": 0.05607103556394577, "part_id": 17}], "image_size": {"width": 314, "height": 628}, "face_landmark": []}, {"body_part": [{"y": 154, "x": 520, "confidence": 0.14941398799419403, "part_id": 0}, {"y": 159, "x": 521, "confidence": 0.32876330614089966, "part_id": 1}, {"y": 159, "x": 508, "confidence": 0.2918807864189148, "part_id": 2}, {"y": 165, "x": 507, "confidence": 0.33272457122802734, "part_id": 3}, {"y": 168, "x": 508, "confidence": 0.26497846841812134, "part_id": 4}, {"y": 159, "x": 522, "confidence": 0.3305813670158386, "part_id": 5}, {"y": 0, "x": 0, "confidence": 0.0, "part_id": 6}, {"y": 0, "x": 0, "confidence": 0.0, "part_id": 7}, {"y": 0, "x": 0, "confidence": 0.0, "part_id": 8}, {"y": 0, "x": 0, "confidence": 0.0, "part_id": 9}, {"y": 0, "x": 0, "confidence": 0.0, "part_id": 10}, {"y": 0, "x": 0, "confidence": 0.0, "part_id": 11}, {"y": 0, "x": 0, "confidence": 0.0, "part_id": 12}, {"y": 0, "x": 0, "confidence": 0.0, "part_id": 13}, {"y": 153, "x": 520, "confidence": 0.08287167549133301, "part_id": 14}, {"y": 153, "x": 521, "confidence": 0.14688235521316528, "part_id": 15}, {"y": 0, "x": 0, "confidence": 0.0, "part_id": 16}, {"y": 153, "x": 521, "confidence": 0.15840840339660645, "part_id": 17}], "image_size": {"width": 314, "height": 628}, "face_landmark": []}, {"body_part": [{"y": 159, "x": 440, "confidence": 0.09470173716545105, "part_id": 0}, {"y": 160, "x": 440, "confidence": 0.5147864818572998, "part_id": 1}, {"y": 160, "x": 440, "confidence": 0.42983973026275635, "part_id": 2}, {"y": 166, "x": 442, "confidence": 0.17449477314949036, "part_id": 3}, {"y": 0, "x": 0, "confidence": 0.0, "part_id": 4}, {"y": 160, "x": 440, "confidence": 0.4726804792881012, "part_id": 5}, {"y": 166, "x": 440, "confidence": 0.32626181840896606, "part_id": 6}, {"y": 169, "x": 440, "confidence": 0.19340862333774567, "part_id": 7}, {"y": 171, "x": 440, "confidence": 0.3197190761566162, "part_id": 8}, {"y": 181, "x": 440, "confidence": 0.14226368069648743, "part_id": 9}, {"y": 188, "x": 439, "confidence": 0.06040285527706146, "part_id": 10}, {"y": 171, "x": 440, "confidence": 0.35737553238868713, "part_id": 11}, {"y": 180, "x": 439, "confidence": 0.17800909280776978, "part_id": 12}, {"y": 188, "x": 438, "confidence": 0.0816064327955246, "part_id": 13}, {"y": 0, "x": 0, "confidence": 0.0, "part_id": 14}, {"y": 157, "x": 439, "confidence": 0.0700908973813057, "part_id": 15}, {"y": 0, "x": 0, "confidence": 0.0, "part_id": 16}, {"y": 157, "x": 440, "confidence": 0.1899430900812149, "part_id": 17}], "image_size": {"width": 314, "height": 628}, "face_landmark": []}, {"body_part": [{"y": 0, "x": 0, "confidence": 0.0, "part_id": 0}, {"y": 167, "x": 56, "confidence": 0.42981451749801636, "part_id": 1}, {"y": 166, "x": 57, "confidence": 0.444685161113739, "part_id": 2}, {"y": 173, "x": 57, "confidence": 0.28254926204681396, "part_id": 3}, {"y": 174, "x": 57, "confidence": 0.13189682364463806, "part_id": 4}, {"y": 167, "x": 54, "confidence": 0.3553711771965027, "part_id": 5}, {"y": 173, "x": 56, "confidence": 0.13173294067382812, "part_id": 6}, {"y": 0, "x": 0, "confidence": 0.0, "part_id": 7}, {"y": 179, "x": 57, "confidence": 0.2202695608139038, "part_id": 8}, {"y": 0, "x": 0, "confidence": 0.0, "part_id": 9}, {"y": 0, "x": 0, "confidence": 0.0, "part_id": 10}, {"y": 180, "x": 57, "confidence": 0.20428690314292908, "part_id": 11}, {"y": 0, "x": 0, "confidence": 0.0, "part_id": 12}, {"y": 0, "x": 0, "confidence": 0.0, "part_id": 13}, {"y": 0, "x": 0, "confidence": 0.0, "part_id": 14}, {"y": 0, "x": 0, "confidence": 0.0, "part_id": 15}, {"y": 0, "x": 0, "confidence": 0.0, "part_id": 16}, {"y": 161, "x": 51, "confidence": 0.05837167426943779, "part_id": 17}], "image_size": {"width": 314, "height": 628}, "face_landmark": []}, {"body_part": [{"y": 0, "x": 0, "confidence": 0.0, "part_id": 0}, {"y": 159, "x": 282, "confidence": 0.29869216680526733, "part_id": 1}, {"y": 159, "x": 282, "confidence": 0.3083729147911072, "part_id": 2}, {"y": 163, "x": 282, "confidence": 0.1932501345872879, "part_id": 3}, {"y": 168, "x": 284, "confidence": 0.14259731769561768, "part_id": 4}, {"y": 0, "x": 0, "confidence": 0.0, "part_id": 5}, {"y": 0, "x": 0, "confidence": 0.0, "part_id": 6}, {"y": 0, "x": 0, "confidence": 0.0, "part_id": 7}, {"y": 169, "x": 282, "confidence": 0.31083008646965027, "part_id": 8}, {"y": 180, "x": 283, "confidence": 0.2533145844936371, "part_id": 9}, {"y": 193, "x": 290, "confidence": 0.14918959140777588, "part_id": 10}, {"y": 168, "x": 282, "confidence": 0.2882480323314667, "part_id": 11}, {"y": 181, "x": 282, "confidence": 0.1954895406961441, "part_id": 12}, {"y": 190, "x": 278, "confidence": 0.07519660890102386, "part_id": 13}, {"y": 0, "x": 0, "confidence": 0.0, "part_id": 14}, {"y": 0, "x": 0, "confidence": 0.0, "part_id": 15}, {"y": 0, "x": 0, "confidence": 0.0, "part_id": 16}, {"y": 0, "x": 0, "confidence": 0.0, "part_id": 17}], "image_size": {"width": 314, "height": 628}, "face_landmark": []}, {"body_part": [{"y": 0, "x": 0, "confidence": 0.0, "part_id": 0}, {"y": 159, "x": 509, "confidence": 0.2999408543109894, "part_id": 1}, {"y": 0, "x": 0, "confidence": 0.0, "part_id": 2}, {"y": 0, "x": 0, "confidence": 0.0, "part_id": 3}, {"y": 0, "x": 0, "confidence": 0.0, "part_id": 4}, {"y": 159, "x": 522, "confidence": 0.3305813670158386, "part_id": 5}, {"y": 165, "x": 524, "confidence": 0.23259879648685455, "part_id": 6}, {"y": 167, "x": 516, "confidence": 0.22846031188964844, "part_id": 7}, {"y": 171, "x": 508, "confidence": 0.33597883582115173, "part_id": 8}, {"y": 179, "x": 507, "confidence": 0.3112327754497528, "part_id": 9}, {"y": 189, "x": 508, "confidence": 0.25223302841186523, "part_id": 10}, {"y": 171, "x": 508, "confidence": 0.2442992627620697, "part_id": 11}, {"y": 180, "x": 508, "confidence": 0.1674259454011917, "part_id": 12}, {"y": 189, "x": 508, "confidence": 0.11874263733625412, "part_id": 13}, {"y": 0, "x": 0, "confidence": 0.0, "part_id": 14}, {"y": 0, "x": 0, "confidence": 0.0, "part_id": 15}, {"y": 0, "x": 0, "confidence": 0.0, "part_id": 16}, {"y": 153, "x": 521, "confidence": 0.15840840339660645, "part_id": 17}], "image_size": {"width": 314, "height": 628}, "face_landmark": []}, {"body_part": [{"y": 0, "x": 0, "confidence": 0.0, "part_id": 0}, {"y": 0, "x": 0, "confidence": 0.0, "part_id": 1}, {"y": 167, "x": 16, "confidence": 0.4943980872631073, "part_id": 2}, {"y": 173, "x": 16, "confidence": 0.389451265335083, "part_id": 3}, {"y": 176, "x": 16, "confidence": 0.23499858379364014, "part_id": 4}, {"y": 0, "x": 0, "confidence": 0.0, "part_id": 5}, {"y": 0, "x": 0, "confidence": 0.0, "part_id": 6}, {"y": 0, "x": 0, "confidence": 0.0, "part_id": 7}, {"y": 0, "x": 0, "confidence": 0.0, "part_id": 8}, {"y": 0, "x": 0, "confidence": 0.0, "part_id": 9}, {"y": 0, "x": 0, "confidence": 0.0, "part_id": 10}, {"y": 0, "x": 0, "confidence": 0.0, "part_id": 11}, {"y": 0, "x": 0, "confidence": 0.0, "part_id": 12}, {"y": 0, "x": 0, "confidence": 0.0, "part_id": 13}, {"y": 0, "x": 0, "confidence": 0.0, "part_id": 14}, {"y": 0, "x": 0, "confidence": 0.0, "part_id": 15}, {"y": 160, "x": 16, "confidence": 0.21767054498195648, "part_id": 16}, {"y": 0, "x": 0, "confidence": 0.0, "part_id": 17}], "image_size": {"width": 314, "height": 628}, "face_landmark": []}, {"body_part": [{"y": 163, "x": 16, "confidence": 0.08452579379081726, "part_id": 0}, {"y": 167, "x": 15, "confidence": 0.4255077540874481, "part_id": 1}, {"y": 0, "x": 0, "confidence": 0.0, "part_id": 2}, {"y": 0, "x": 0, "confidence": 0.0, "part_id": 3}, {"y": 0, "x": 0, "confidence": 0.0, "part_id": 4}, {"y": 0, "x": 0, "confidence": 0.0, "part_id": 5}, {"y": 0, "x": 0, "confidence": 0.0, "part_id": 6}, {"y": 0, "x": 0, "confidence": 0.0, "part_id": 7}, {"y": 183, "x": 15, "confidence": 0.32747945189476013, "part_id": 8}, {"y": 194, "x": 11, "confidence": 0.18722379207611084, "part_id": 9}, {"y": 206, "x": 9, "confidence": 0.11977528780698776, "part_id": 10}, {"y": 182, "x": 13, "confidence": 0.25446251034736633, "part_id": 11}, {"y": 195, "x": 11, "confidence": 0.1948907971382141, "part_id": 12}, {"y": 202, "x": 9, "confidence": 0.11074753105640411, "part_id": 13}, {"y": 161, "x": 16, "confidence": 0.09014443308115005, "part_id": 14}, {"y": 0, "x": 0, "confidence": 0.0, "part_id": 15}, {"y": 0, "x": 0, "confidence": 0.0, "part_id": 16}, {"y": 0, "x": 0, "confidence": 0.0, "part_id": 17}], "image_size": {"width": 314, "height": 628}, "face_landmark": []}]